{"tileW":24,"tileH":24,"atlasW":768,"atlasH":1104,"tileCount":1467,"tiles":{"1,0":{"ax":0,"ay":0},"2,0":{"ax":24,"ay":0},"2,1":{"ax":48,"ay":0},"2,2":{"ax":72,"ay":0},"2,3":{"ax":96,"ay":0},"3,0":{"ax":120,"ay":0},"3,1":{"ax":144,"ay":0},"3,2":{"ax":168,"ay":0},"3,3":{"ax":192,"ay":0},"3,4":{"ax":216,"ay":0},"3,5":{"ax":240,"ay":0},"3,6":{"ax":264,"ay":0},"3,7":{"ax":288,"ay":0},"3,8":{"ax":312,"ay":0},"3,9":{"ax":336,"ay":0},"3,10":{"ax":360,"ay":0},"4,0":{"ax":384,"ay":0},"4,1":{"ax":408,"ay":0},"4,2":{"ax":432,"ay":0},"4,3":{"ax":456,"ay":0},"4,4":{"ax":480,"ay":0},"4,5":{"ax":504,"ay":0},"4,6":{"ax":528,"ay":0},"4,7":{"ax":552,"ay":0},"4,8":{"ax":576,"ay":0},"4,9":{"ax":600,"ay":0},"4,10":{"ax":624,"ay":0},"4,11":{"ax":648,"ay":0},"4,12":{"ax":672,"ay":0},"4,13":{"ax":696,"ay":0},"4,14":{"ax":720,"ay":0},"5,0":{"ax":744,"ay":0},"5,1":{"ax":0,"ay":24},"5,2":{"ax":24,"ay":24},"5,3":{"ax":48,"ay":24},"5,4":{"ax":72,"ay":24},"5,5":{"ax":96,"ay":24},"5,6":{"ax":120,"ay":24},"5,7":{"ax":144,"ay":24},"5,8":{"ax":168,"ay":24},"6,0":{"ax":192,"ay":24},"6,1":{"ax":216,"ay":24},"6,2":{"ax":240,"ay":24},"6,3":{"ax":264,"ay":24},"6,4":{"ax":288,"ay":24},"6,5":{"ax":312,"ay":24},"6,6":{"ax":336,"ay":24},"6,7":{"ax":360,"ay":24},"6,8":{"ax":384,"ay":24},"7,0":{"ax":408,"ay":24},"7,1":{"ax":432,"ay":24},"7,2":{"ax":456,"ay":24},"7,3":{"ax":480,"ay":24},"7,4":{"ax":504,"ay":24},"7,5":{"ax":528,"ay":24},"7,6":{"ax":552,"ay":24},"7,7":{"ax":576,"ay":24},"7,8":{"ax":600,"ay":24},"8,0":{"ax":624,"ay":24},"8,1":{"ax":648,"ay":24},"8,2":{"ax":672,"ay":24},"8,3":{"ax":696,"ay":24},"8,4":{"ax":720,"ay":24},"8,5":{"ax":744,"ay":24},"8,6":{"ax":0,"ay":48},"8,7":{"ax":24,"ay":48},"8,8":{"ax":48,"ay":48},"9,0":{"ax":72,"ay":48},"9,1":{"ax":96,"ay":48},"9,2":{"ax":120,"ay":48},"9,3":{"ax":144,"ay":48},"9,4":{"ax":168,"ay":48},"9,5":{"ax":192,"ay":48},"9,6":{"ax":216,"ay":48},"9,7":{"ax":240,"ay":48},"9,8":{"ax":264,"ay":48},"10,0":{"ax":288,"ay":48},"10,1":{"ax":312,"ay":48},"11,0":{"ax":336,"ay":48},"11,1":{"ax":360,"ay":48},"11,2":{"ax":384,"ay":48},"11,3":{"ax":408,"ay":48},"11,4":{"ax":432,"ay":48},"11,5":{"ax":456,"ay":48},"11,6":{"ax":480,"ay":48},"11,7":{"ax":504,"ay":48},"11,8":{"ax":528,"ay":48},"12,0":{"ax":552,"ay":48},"12,1":{"ax":576,"ay":48},"12,2":{"ax":600,"ay":48},"12,3":{"ax":624,"ay":48},"12,4":{"ax":648,"ay":48},"12,5":{"ax":672,"ay":48},"12,6":{"ax":696,"ay":48},"12,7":{"ax":720,"ay":48},"12,8":{"ax":744,"ay":48},"12,9":{"ax":0,"ay":72},"12,10":{"ax":24,"ay":72},"12,11":{"ax":48,"ay":72},"12,12":{"ax":72,"ay":72},"12,13":{"ax":96,"ay":72},"12,14":{"ax":120,"ay":72},"13,0":{"ax":144,"ay":72},"13,1":{"ax":168,"ay":72},"13,2":{"ax":192,"ay":72},"13,3":{"ax":216,"ay":72},"13,4":{"ax":240,"ay":72},"13,5":{"ax":264,"ay":72},"13,6":{"ax":288,"ay":72},"13,7":{"ax":312,"ay":72},"13,8":{"ax":336,"ay":72},"13,9":{"ax":360,"ay":72},"13,10":{"ax":384,"ay":72},"13,11":{"ax":408,"ay":72},"13,12":{"ax":432,"ay":72},"14,0":{"ax":456,"ay":72},"14,1":{"ax":480,"ay":72},"14,2":{"ax":504,"ay":72},"14,3":{"ax":528,"ay":72},"14,4":{"ax":552,"ay":72},"14,5":{"ax":576,"ay":72},"14,6":{"ax":600,"ay":72},"14,7":{"ax":624,"ay":72},"14,8":{"ax":648,"ay":72},"14,9":{"ax":672,"ay":72},"14,10":{"ax":696,"ay":72},"15,0":{"ax":720,"ay":72},"15,1":{"ax":744,"ay":72},"15,2":{"ax":0,"ay":96},"15,3":{"ax":24,"ay":96},"15,4":{"ax":48,"ay":96},"15,5":{"ax":72,"ay":96},"15,6":{"ax":96,"ay":96},"15,7":{"ax":120,"ay":96},"15,8":{"ax":144,"ay":96},"15,9":{"ax":168,"ay":96},"15,10":{"ax":192,"ay":96},"15,11":{"ax":216,"ay":96},"15,12":{"ax":240,"ay":96},"15,13":{"ax":264,"ay":96},"15,14":{"ax":288,"ay":96},"15,15":{"ax":312,"ay":96},"15,16":{"ax":336,"ay":96},"15,17":{"ax":360,"ay":96},"16,0":{"ax":384,"ay":96},"16,1":{"ax":408,"ay":96},"16,2":{"ax":432,"ay":96},"16,3":{"ax":456,"ay":96},"16,4":{"ax":480,"ay":96},"16,5":{"ax":504,"ay":96},"16,6":{"ax":528,"ay":96},"16,7":{"ax":552,"ay":96},"16,8":{"ax":576,"ay":96},"16,9":{"ax":600,"ay":96},"16,10":{"ax":624,"ay":96},"16,11":{"ax":648,"ay":96},"17,0":{"ax":672,"ay":96},"17,1":{"ax":696,"ay":96},"17,2":{"ax":720,"ay":96},"17,3":{"ax":744,"ay":96},"17,4":{"ax":0,"ay":120},"17,5":{"ax":24,"ay":120},"17,6":{"ax":48,"ay":120},"17,7":{"ax":72,"ay":120},"17,8":{"ax":96,"ay":120},"17,9":{"ax":120,"ay":120},"18,0":{"ax":144,"ay":120},"18,1":{"ax":168,"ay":120},"18,2":{"ax":192,"ay":120},"18,3":{"ax":216,"ay":120},"18,4":{"ax":240,"ay":120},"18,5":{"ax":264,"ay":120},"18,6":{"ax":288,"ay":120},"18,7":{"ax":312,"ay":120},"18,8":{"ax":336,"ay":120},"19,0":{"ax":360,"ay":120},"19,1":{"ax":384,"ay":120},"20,0":{"ax":408,"ay":120},"20,1":{"ax":432,"ay":120},"20,2":{"ax":456,"ay":120},"20,3":{"ax":480,"ay":120},"20,4":{"ax":504,"ay":120},"20,5":{"ax":528,"ay":120},"20,6":{"ax":552,"ay":120},"20,7":{"ax":576,"ay":120},"20,8":{"ax":600,"ay":120},"21,0":{"ax":624,"ay":120},"21,1":{"ax":648,"ay":120},"21,2":{"ax":672,"ay":120},"21,3":{"ax":696,"ay":120},"21,4":{"ax":720,"ay":120},"21,5":{"ax":744,"ay":120},"21,6":{"ax":0,"ay":144},"21,7":{"ax":24,"ay":144},"21,8":{"ax":48,"ay":144},"21,9":{"ax":72,"ay":144},"21,10":{"ax":96,"ay":144},"21,11":{"ax":120,"ay":144},"21,12":{"ax":144,"ay":144},"21,13":{"ax":168,"ay":144},"21,14":{"ax":192,"ay":144},"22,0":{"ax":216,"ay":144},"22,1":{"ax":240,"ay":144},"22,2":{"ax":264,"ay":144},"22,3":{"ax":288,"ay":144},"22,4":{"ax":312,"ay":144},"22,5":{"ax":336,"ay":144},"22,6":{"ax":360,"ay":144},"22,7":{"ax":384,"ay":144},"22,8":{"ax":408,"ay":144},"22,9":{"ax":432,"ay":144},"22,10":{"ax":456,"ay":144},"22,11":{"ax":480,"ay":144},"22,12":{"ax":504,"ay":144},"23,0":{"ax":528,"ay":144},"23,1":{"ax":552,"ay":144},"23,2":{"ax":576,"ay":144},"23,3":{"ax":600,"ay":144},"23,4":{"ax":624,"ay":144},"23,5":{"ax":648,"ay":144},"23,6":{"ax":672,"ay":144},"23,7":{"ax":696,"ay":144},"23,8":{"ax":720,"ay":144},"23,9":{"ax":744,"ay":144},"23,10":{"ax":0,"ay":168},"24,0":{"ax":24,"ay":168},"24,1":{"ax":48,"ay":168},"24,2":{"ax":72,"ay":168},"24,3":{"ax":96,"ay":168},"24,4":{"ax":120,"ay":168},"24,5":{"ax":144,"ay":168},"24,6":{"ax":168,"ay":168},"24,7":{"ax":192,"ay":168},"24,8":{"ax":216,"ay":168},"24,9":{"ax":240,"ay":168},"24,10":{"ax":264,"ay":168},"24,11":{"ax":288,"ay":168},"24,12":{"ax":312,"ay":168},"24,13":{"ax":336,"ay":168},"24,14":{"ax":360,"ay":168},"24,15":{"ax":384,"ay":168},"24,16":{"ax":408,"ay":168},"25,0":{"ax":432,"ay":168},"25,1":{"ax":456,"ay":168},"25,2":{"ax":480,"ay":168},"25,3":{"ax":504,"ay":168},"25,4":{"ax":528,"ay":168},"25,5":{"ax":552,"ay":168},"25,6":{"ax":576,"ay":168},"25,7":{"ax":600,"ay":168},"25,8":{"ax":624,"ay":168},"25,9":{"ax":648,"ay":168},"25,10":{"ax":672,"ay":168},"25,11":{"ax":696,"ay":168},"25,12":{"ax":720,"ay":168},"25,13":{"ax":744,"ay":168},"25,14":{"ax":0,"ay":192},"25,15":{"ax":24,"ay":192},"25,16":{"ax":48,"ay":192},"25,17":{"ax":72,"ay":192},"26,0":{"ax":96,"ay":192},"26,1":{"ax":120,"ay":192},"26,2":{"ax":144,"ay":192},"26,3":{"ax":168,"ay":192},"26,4":{"ax":192,"ay":192},"26,5":{"ax":216,"ay":192},"26,6":{"ax":240,"ay":192},"26,7":{"ax":264,"ay":192},"27,0":{"ax":288,"ay":192},"27,1":{"ax":312,"ay":192},"27,2":{"ax":336,"ay":192},"27,3":{"ax":360,"ay":192},"27,4":{"ax":384,"ay":192},"27,5":{"ax":408,"ay":192},"27,6":{"ax":432,"ay":192},"27,7":{"ax":456,"ay":192},"27,8":{"ax":480,"ay":192},"28,0":{"ax":504,"ay":192},"28,1":{"ax":528,"ay":192},"28,2":{"ax":552,"ay":192},"28,3":{"ax":576,"ay":192},"28,4":{"ax":600,"ay":192},"28,5":{"ax":624,"ay":192},"28,6":{"ax":648,"ay":192},"28,7":{"ax":672,"ay":192},"28,8":{"ax":696,"ay":192},"29,0":{"ax":720,"ay":192},"29,1":{"ax":744,"ay":192},"29,2":{"ax":0,"ay":216},"29,3":{"ax":24,"ay":216},"29,4":{"ax":48,"ay":216},"29,5":{"ax":72,"ay":216},"29,6":{"ax":96,"ay":216},"29,7":{"ax":120,"ay":216},"29,8":{"ax":144,"ay":216},"30,0":{"ax":168,"ay":216},"30,1":{"ax":192,"ay":216},"30,2":{"ax":216,"ay":216},"30,3":{"ax":240,"ay":216},"30,4":{"ax":264,"ay":216},"30,5":{"ax":288,"ay":216},"30,6":{"ax":312,"ay":216},"30,7":{"ax":336,"ay":216},"31,0":{"ax":360,"ay":216},"31,1":{"ax":384,"ay":216},"32,0":{"ax":408,"ay":216},"32,1":{"ax":432,"ay":216},"32,2":{"ax":456,"ay":216},"32,3":{"ax":480,"ay":216},"32,4":{"ax":504,"ay":216},"32,5":{"ax":528,"ay":216},"33,0":{"ax":552,"ay":216},"33,1":{"ax":576,"ay":216},"33,2":{"ax":600,"ay":216},"33,3":{"ax":624,"ay":216},"33,4":{"ax":648,"ay":216},"33,5":{"ax":672,"ay":216},"33,6":{"ax":696,"ay":216},"33,7":{"ax":720,"ay":216},"33,8":{"ax":744,"ay":216},"33,9":{"ax":0,"ay":240},"33,10":{"ax":24,"ay":240},"33,11":{"ax":48,"ay":240},"33,12":{"ax":72,"ay":240},"33,13":{"ax":96,"ay":240},"33,14":{"ax":120,"ay":240},"33,15":{"ax":144,"ay":240},"33,16":{"ax":168,"ay":240},"33,17":{"ax":192,"ay":240},"33,18":{"ax":216,"ay":240},"33,19":{"ax":240,"ay":240},"33,20":{"ax":264,"ay":240},"33,21":{"ax":288,"ay":240},"34,0":{"ax":312,"ay":240},"34,1":{"ax":336,"ay":240},"34,2":{"ax":360,"ay":240},"34,3":{"ax":384,"ay":240},"34,4":{"ax":408,"ay":240},"34,5":{"ax":432,"ay":240},"34,6":{"ax":456,"ay":240},"34,7":{"ax":480,"ay":240},"34,8":{"ax":504,"ay":240},"34,9":{"ax":528,"ay":240},"34,10":{"ax":552,"ay":240},"35,0":{"ax":576,"ay":240},"35,1":{"ax":600,"ay":240},"35,2":{"ax":624,"ay":240},"35,3":{"ax":648,"ay":240},"35,4":{"ax":672,"ay":240},"35,5":{"ax":696,"ay":240},"35,6":{"ax":720,"ay":240},"35,7":{"ax":744,"ay":240},"35,8":{"ax":0,"ay":264},"36,0":{"ax":24,"ay":264},"36,1":{"ax":48,"ay":264},"36,2":{"ax":72,"ay":264},"36,3":{"ax":96,"ay":264},"36,4":{"ax":120,"ay":264},"36,5":{"ax":144,"ay":264},"36,6":{"ax":168,"ay":264},"36,7":{"ax":192,"ay":264},"36,8":{"ax":216,"ay":264},"36,9":{"ax":240,"ay":264},"36,10":{"ax":264,"ay":264},"36,11":{"ax":288,"ay":264},"36,12":{"ax":312,"ay":264},"36,13":{"ax":336,"ay":264},"36,14":{"ax":360,"ay":264},"36,15":{"ax":384,"ay":264},"37,0":{"ax":408,"ay":264},"37,1":{"ax":432,"ay":264},"37,2":{"ax":456,"ay":264},"37,3":{"ax":480,"ay":264},"37,4":{"ax":504,"ay":264},"37,5":{"ax":528,"ay":264},"37,6":{"ax":552,"ay":264},"37,7":{"ax":576,"ay":264},"37,8":{"ax":600,"ay":264},"37,9":{"ax":624,"ay":264},"37,10":{"ax":648,"ay":264},"38,0":{"ax":672,"ay":264},"38,1":{"ax":696,"ay":264},"38,2":{"ax":720,"ay":264},"38,3":{"ax":744,"ay":264},"38,4":{"ax":0,"ay":288},"38,5":{"ax":24,"ay":288},"38,6":{"ax":48,"ay":288},"38,7":{"ax":72,"ay":288},"38,8":{"ax":96,"ay":288},"39,0":{"ax":120,"ay":288},"39,1":{"ax":144,"ay":288},"39,2":{"ax":168,"ay":288},"39,3":{"ax":192,"ay":288},"39,4":{"ax":216,"ay":288},"39,5":{"ax":240,"ay":288},"39,6":{"ax":264,"ay":288},"39,7":{"ax":288,"ay":288},"40,0":{"ax":312,"ay":288},"40,1":{"ax":336,"ay":288},"41,0":{"ax":360,"ay":288},"41,1":{"ax":384,"ay":288},"41,2":{"ax":408,"ay":288},"41,3":{"ax":432,"ay":288},"41,4":{"ax":456,"ay":288},"41,5":{"ax":480,"ay":288},"41,6":{"ax":504,"ay":288},"41,7":{"ax":528,"ay":288},"41,8":{"ax":552,"ay":288},"42,0":{"ax":576,"ay":288},"42,1":{"ax":600,"ay":288},"42,2":{"ax":624,"ay":288},"42,3":{"ax":648,"ay":288},"42,4":{"ax":672,"ay":288},"42,5":{"ax":696,"ay":288},"42,6":{"ax":720,"ay":288},"42,7":{"ax":744,"ay":288},"42,8":{"ax":0,"ay":312},"42,9":{"ax":24,"ay":312},"42,10":{"ax":48,"ay":312},"42,11":{"ax":72,"ay":312},"42,12":{"ax":96,"ay":312},"42,13":{"ax":120,"ay":312},"42,14":{"ax":144,"ay":312},"43,0":{"ax":168,"ay":312},"43,1":{"ax":192,"ay":312},"43,2":{"ax":216,"ay":312},"43,3":{"ax":240,"ay":312},"43,4":{"ax":264,"ay":312},"43,5":{"ax":288,"ay":312},"43,6":{"ax":312,"ay":312},"43,7":{"ax":336,"ay":312},"43,8":{"ax":360,"ay":312},"43,9":{"ax":384,"ay":312},"43,10":{"ax":408,"ay":312},"43,11":{"ax":432,"ay":312},"44,0":{"ax":456,"ay":312},"44,1":{"ax":480,"ay":312},"44,2":{"ax":504,"ay":312},"44,3":{"ax":528,"ay":312},"44,4":{"ax":552,"ay":312},"44,5":{"ax":576,"ay":312},"44,6":{"ax":600,"ay":312},"44,7":{"ax":624,"ay":312},"44,8":{"ax":648,"ay":312},"45,0":{"ax":672,"ay":312},"45,1":{"ax":696,"ay":312},"45,2":{"ax":720,"ay":312},"45,3":{"ax":744,"ay":312},"45,4":{"ax":0,"ay":336},"45,5":{"ax":24,"ay":336},"45,6":{"ax":48,"ay":336},"45,7":{"ax":72,"ay":336},"45,8":{"ax":96,"ay":336},"46,0":{"ax":120,"ay":336},"46,1":{"ax":144,"ay":336},"46,2":{"ax":168,"ay":336},"46,3":{"ax":192,"ay":336},"47,0":{"ax":216,"ay":336},"47,1":{"ax":240,"ay":336},"47,2":{"ax":264,"ay":336},"47,3":{"ax":288,"ay":336},"47,4":{"ax":312,"ay":336},"47,5":{"ax":336,"ay":336},"47,6":{"ax":360,"ay":336},"47,7":{"ax":384,"ay":336},"47,8":{"ax":408,"ay":336},"48,0":{"ax":432,"ay":336},"48,1":{"ax":456,"ay":336},"48,2":{"ax":480,"ay":336},"48,3":{"ax":504,"ay":336},"49,0":{"ax":528,"ay":336},"49,1":{"ax":552,"ay":336},"49,2":{"ax":576,"ay":336},"49,3":{"ax":600,"ay":336},"49,4":{"ax":624,"ay":336},"49,5":{"ax":648,"ay":336},"50,0":{"ax":672,"ay":336},"50,1":{"ax":696,"ay":336},"50,2":{"ax":720,"ay":336},"50,3":{"ax":744,"ay":336},"51,0":{"ax":0,"ay":360},"51,1":{"ax":24,"ay":360},"51,2":{"ax":48,"ay":360},"51,3":{"ax":72,"ay":360},"51,4":{"ax":96,"ay":360},"51,5":{"ax":120,"ay":360},"51,6":{"ax":144,"ay":360},"51,7":{"ax":168,"ay":360},"51,8":{"ax":192,"ay":360},"52,0":{"ax":216,"ay":360},"52,1":{"ax":240,"ay":360},"52,2":{"ax":264,"ay":360},"52,3":{"ax":288,"ay":360},"53,0":{"ax":312,"ay":360},"53,1":{"ax":336,"ay":360},"53,2":{"ax":360,"ay":360},"53,3":{"ax":384,"ay":360},"53,4":{"ax":408,"ay":360},"53,5":{"ax":432,"ay":360},"53,6":{"ax":456,"ay":360},"54,0":{"ax":480,"ay":360},"54,1":{"ax":504,"ay":360},"54,2":{"ax":528,"ay":360},"54,3":{"ax":552,"ay":360},"54,4":{"ax":576,"ay":360},"54,5":{"ax":600,"ay":360},"54,6":{"ax":624,"ay":360},"55,0":{"ax":648,"ay":360},"55,1":{"ax":672,"ay":360},"55,2":{"ax":696,"ay":360},"55,3":{"ax":720,"ay":360},"55,4":{"ax":744,"ay":360},"55,5":{"ax":0,"ay":384},"55,6":{"ax":24,"ay":384},"55,7":{"ax":48,"ay":384},"56,0":{"ax":72,"ay":384},"56,1":{"ax":96,"ay":384},"56,2":{"ax":120,"ay":384},"56,3":{"ax":144,"ay":384},"56,4":{"ax":168,"ay":384},"56,5":{"ax":192,"ay":384},"57,0":{"ax":216,"ay":384},"58,0":{"ax":240,"ay":384},"58,1":{"ax":264,"ay":384},"59,0":{"ax":288,"ay":384},"59,1":{"ax":312,"ay":384},"59,2":{"ax":336,"ay":384},"59,3":{"ax":360,"ay":384},"60,0":{"ax":384,"ay":384},"60,1":{"ax":408,"ay":384},"60,2":{"ax":432,"ay":384},"60,3":{"ax":456,"ay":384},"60,4":{"ax":480,"ay":384},"60,5":{"ax":504,"ay":384},"61,0":{"ax":528,"ay":384},"61,1":{"ax":552,"ay":384},"61,2":{"ax":576,"ay":384},"61,3":{"ax":600,"ay":384},"62,0":{"ax":624,"ay":384},"62,1":{"ax":648,"ay":384},"62,2":{"ax":672,"ay":384},"62,3":{"ax":696,"ay":384},"63,0":{"ax":720,"ay":384},"63,1":{"ax":744,"ay":384},"63,2":{"ax":0,"ay":408},"63,3":{"ax":24,"ay":408},"64,0":{"ax":48,"ay":408},"64,1":{"ax":72,"ay":408},"64,2":{"ax":96,"ay":408},"64,3":{"ax":120,"ay":408},"64,4":{"ax":144,"ay":408},"65,0":{"ax":168,"ay":408},"65,1":{"ax":192,"ay":408},"65,2":{"ax":216,"ay":408},"65,3":{"ax":240,"ay":408},"66,0":{"ax":264,"ay":408},"66,1":{"ax":288,"ay":408},"66,2":{"ax":312,"ay":408},"66,3":{"ax":336,"ay":408},"67,0":{"ax":360,"ay":408},"67,1":{"ax":384,"ay":408},"67,2":{"ax":408,"ay":408},"67,3":{"ax":432,"ay":408},"67,4":{"ax":456,"ay":408},"67,5":{"ax":480,"ay":408},"68,0":{"ax":504,"ay":408},"68,1":{"ax":528,"ay":408},"68,2":{"ax":552,"ay":408},"68,3":{"ax":576,"ay":408},"69,0":{"ax":600,"ay":408},"69,1":{"ax":624,"ay":408},"69,2":{"ax":648,"ay":408},"69,3":{"ax":672,"ay":408},"70,0":{"ax":696,"ay":408},"70,1":{"ax":720,"ay":408},"70,2":{"ax":744,"ay":408},"70,3":{"ax":0,"ay":432},"71,0":{"ax":24,"ay":432},"71,1":{"ax":48,"ay":432},"71,2":{"ax":72,"ay":432},"71,3":{"ax":96,"ay":432},"71,4":{"ax":120,"ay":432},"71,5":{"ax":144,"ay":432},"72,0":{"ax":168,"ay":432},"72,1":{"ax":192,"ay":432},"72,2":{"ax":216,"ay":432},"72,3":{"ax":240,"ay":432},"73,0":{"ax":264,"ay":432},"73,1":{"ax":288,"ay":432},"73,2":{"ax":312,"ay":432},"73,3":{"ax":336,"ay":432},"74,0":{"ax":360,"ay":432},"74,1":{"ax":384,"ay":432},"74,2":{"ax":408,"ay":432},"74,3":{"ax":432,"ay":432},"75,0":{"ax":456,"ay":432},"75,1":{"ax":480,"ay":432},"75,2":{"ax":504,"ay":432},"75,3":{"ax":528,"ay":432},"76,0":{"ax":552,"ay":432},"76,1":{"ax":576,"ay":432},"76,2":{"ax":600,"ay":432},"76,3":{"ax":624,"ay":432},"77,0":{"ax":648,"ay":432},"77,1":{"ax":672,"ay":432},"77,2":{"ax":696,"ay":432},"77,3":{"ax":720,"ay":432},"78,0":{"ax":744,"ay":432},"78,1":{"ax":0,"ay":456},"78,2":{"ax":24,"ay":456},"78,3":{"ax":48,"ay":456},"78,4":{"ax":72,"ay":456},"79,0":{"ax":96,"ay":456},"79,1":{"ax":120,"ay":456},"80,0":{"ax":144,"ay":456},"80,1":{"ax":168,"ay":456},"80,2":{"ax":192,"ay":456},"80,3":{"ax":216,"ay":456},"81,0":{"ax":240,"ay":456},"81,1":{"ax":264,"ay":456},"81,2":{"ax":288,"ay":456},"81,3":{"ax":312,"ay":456},"81,4":{"ax":336,"ay":456},"81,5":{"ax":360,"ay":456},"82,0":{"ax":384,"ay":456},"82,1":{"ax":408,"ay":456},"82,2":{"ax":432,"ay":456},"82,3":{"ax":456,"ay":456},"83,0":{"ax":480,"ay":456},"83,1":{"ax":504,"ay":456},"83,2":{"ax":528,"ay":456},"83,3":{"ax":552,"ay":456},"84,0":{"ax":576,"ay":456},"84,1":{"ax":600,"ay":456},"84,2":{"ax":624,"ay":456},"84,3":{"ax":648,"ay":456},"85,0":{"ax":672,"ay":456},"85,1":{"ax":696,"ay":456},"85,2":{"ax":720,"ay":456},"85,3":{"ax":744,"ay":456},"85,4":{"ax":0,"ay":480},"85,5":{"ax":24,"ay":480},"86,0":{"ax":48,"ay":480},"86,1":{"ax":72,"ay":480},"86,2":{"ax":96,"ay":480},"87,0":{"ax":120,"ay":480},"87,1":{"ax":144,"ay":480},"87,2":{"ax":168,"ay":480},"87,3":{"ax":192,"ay":480},"88,0":{"ax":216,"ay":480},"88,1":{"ax":240,"ay":480},"88,2":{"ax":264,"ay":480},"88,3":{"ax":288,"ay":480},"89,0":{"ax":312,"ay":480},"89,1":{"ax":336,"ay":480},"89,2":{"ax":360,"ay":480},"89,3":{"ax":384,"ay":480},"90,0":{"ax":408,"ay":480},"90,1":{"ax":432,"ay":480},"90,2":{"ax":456,"ay":480},"91,0":{"ax":480,"ay":480},"91,1":{"ax":504,"ay":480},"91,2":{"ax":528,"ay":480},"91,3":{"ax":552,"ay":480},"92,0":{"ax":576,"ay":480},"92,1":{"ax":600,"ay":480},"92,2":{"ax":624,"ay":480},"92,3":{"ax":648,"ay":480},"93,0":{"ax":672,"ay":480},"93,1":{"ax":696,"ay":480},"93,2":{"ax":720,"ay":480},"93,3":{"ax":744,"ay":480},"94,0":{"ax":0,"ay":504},"94,1":{"ax":24,"ay":504},"94,2":{"ax":48,"ay":504},"94,3":{"ax":72,"ay":504},"95,0":{"ax":96,"ay":504},"95,1":{"ax":120,"ay":504},"95,2":{"ax":144,"ay":504},"95,3":{"ax":168,"ay":504},"96,0":{"ax":192,"ay":504},"96,1":{"ax":216,"ay":504},"96,2":{"ax":240,"ay":504},"96,3":{"ax":264,"ay":504},"97,0":{"ax":288,"ay":504},"98,0":{"ax":312,"ay":504},"98,1":{"ax":336,"ay":504},"99,0":{"ax":360,"ay":504},"99,1":{"ax":384,"ay":504},"99,2":{"ax":408,"ay":504},"103,0":{"ax":432,"ay":504},"104,0":{"ax":456,"ay":504},"105,0":{"ax":480,"ay":504},"106,0":{"ax":504,"ay":504},"107,0":{"ax":528,"ay":504},"107,1":{"ax":552,"ay":504},"107,2":{"ax":576,"ay":504},"107,3":{"ax":600,"ay":504},"107,4":{"ax":624,"ay":504},"107,5":{"ax":648,"ay":504},"107,6":{"ax":672,"ay":504},"107,7":{"ax":696,"ay":504},"108,0":{"ax":720,"ay":504},"108,1":{"ax":744,"ay":504},"108,2":{"ax":0,"ay":528},"108,3":{"ax":24,"ay":528},"108,4":{"ax":48,"ay":528},"108,5":{"ax":72,"ay":528},"109,0":{"ax":96,"ay":528},"109,1":{"ax":120,"ay":528},"109,2":{"ax":144,"ay":528},"109,3":{"ax":168,"ay":528},"109,4":{"ax":192,"ay":528},"109,5":{"ax":216,"ay":528},"110,0":{"ax":240,"ay":528},"110,1":{"ax":264,"ay":528},"112,0":{"ax":288,"ay":528},"112,1":{"ax":312,"ay":528},"112,2":{"ax":336,"ay":528},"112,3":{"ax":360,"ay":528},"112,4":{"ax":384,"ay":528},"112,5":{"ax":408,"ay":528},"112,6":{"ax":432,"ay":528},"112,7":{"ax":456,"ay":528},"112,8":{"ax":480,"ay":528},"112,9":{"ax":504,"ay":528},"112,10":{"ax":528,"ay":528},"112,11":{"ax":552,"ay":528},"112,12":{"ax":576,"ay":528},"112,13":{"ax":600,"ay":528},"113,0":{"ax":624,"ay":528},"113,1":{"ax":648,"ay":528},"113,2":{"ax":672,"ay":528},"113,3":{"ax":696,"ay":528},"113,4":{"ax":720,"ay":528},"113,5":{"ax":744,"ay":528},"113,6":{"ax":0,"ay":552},"113,7":{"ax":24,"ay":552},"113,8":{"ax":48,"ay":552},"113,9":{"ax":72,"ay":552},"113,10":{"ax":96,"ay":552},"113,11":{"ax":120,"ay":552},"113,12":{"ax":144,"ay":552},"114,0":{"ax":168,"ay":552},"114,1":{"ax":192,"ay":552},"114,2":{"ax":216,"ay":552},"114,3":{"ax":240,"ay":552},"114,4":{"ax":264,"ay":552},"114,5":{"ax":288,"ay":552},"114,6":{"ax":312,"ay":552},"114,7":{"ax":336,"ay":552},"114,8":{"ax":360,"ay":552},"114,9":{"ax":384,"ay":552},"114,10":{"ax":408,"ay":552},"114,11":{"ax":432,"ay":552},"114,12":{"ax":456,"ay":552},"115,0":{"ax":480,"ay":552},"115,1":{"ax":504,"ay":552},"115,2":{"ax":528,"ay":552},"115,3":{"ax":552,"ay":552},"115,4":{"ax":576,"ay":552},"115,5":{"ax":600,"ay":552},"115,6":{"ax":624,"ay":552},"115,7":{"ax":648,"ay":552},"115,8":{"ax":672,"ay":552},"115,9":{"ax":696,"ay":552},"115,10":{"ax":720,"ay":552},"115,11":{"ax":744,"ay":552},"116,0":{"ax":0,"ay":576},"116,1":{"ax":24,"ay":576},"116,2":{"ax":48,"ay":576},"116,3":{"ax":72,"ay":576},"116,4":{"ax":96,"ay":576},"116,5":{"ax":120,"ay":576},"116,6":{"ax":144,"ay":576},"116,7":{"ax":168,"ay":576},"116,8":{"ax":192,"ay":576},"117,0":{"ax":216,"ay":576},"117,1":{"ax":240,"ay":576},"117,2":{"ax":264,"ay":576},"117,3":{"ax":288,"ay":576},"117,4":{"ax":312,"ay":576},"117,5":{"ax":336,"ay":576},"118,0":{"ax":360,"ay":576},"118,1":{"ax":384,"ay":576},"118,2":{"ax":408,"ay":576},"118,3":{"ax":432,"ay":576},"118,4":{"ax":456,"ay":576},"118,5":{"ax":480,"ay":576},"119,0":{"ax":504,"ay":576},"119,1":{"ax":528,"ay":576},"119,2":{"ax":552,"ay":576},"119,3":{"ax":576,"ay":576},"120,0":{"ax":600,"ay":576},"120,1":{"ax":624,"ay":576},"120,2":{"ax":648,"ay":576},"120,3":{"ax":672,"ay":576},"121,0":{"ax":696,"ay":576},"121,1":{"ax":720,"ay":576},"121,2":{"ax":744,"ay":576},"121,3":{"ax":0,"ay":600},"122,0":{"ax":24,"ay":600},"122,1":{"ax":48,"ay":600},"122,2":{"ax":72,"ay":600},"122,3":{"ax":96,"ay":600},"123,0":{"ax":120,"ay":600},"123,1":{"ax":144,"ay":600},"123,2":{"ax":168,"ay":600},"123,3":{"ax":192,"ay":600},"123,4":{"ax":216,"ay":600},"123,5":{"ax":240,"ay":600},"123,6":{"ax":264,"ay":600},"123,7":{"ax":288,"ay":600},"123,8":{"ax":312,"ay":600},"123,9":{"ax":336,"ay":600},"123,10":{"ax":360,"ay":600},"123,11":{"ax":384,"ay":600},"124,0":{"ax":408,"ay":600},"124,1":{"ax":432,"ay":600},"124,2":{"ax":456,"ay":600},"124,3":{"ax":480,"ay":600},"124,4":{"ax":504,"ay":600},"124,5":{"ax":528,"ay":600},"124,6":{"ax":552,"ay":600},"124,7":{"ax":576,"ay":600},"124,8":{"ax":600,"ay":600},"124,9":{"ax":624,"ay":600},"124,10":{"ax":648,"ay":600},"124,11":{"ax":672,"ay":600},"124,12":{"ax":696,"ay":600},"124,13":{"ax":720,"ay":600},"125,0":{"ax":744,"ay":600},"125,1":{"ax":0,"ay":624},"125,2":{"ax":24,"ay":624},"125,3":{"ax":48,"ay":624},"125,4":{"ax":72,"ay":624},"125,5":{"ax":96,"ay":624},"125,6":{"ax":120,"ay":624},"125,7":{"ax":144,"ay":624},"125,8":{"ax":168,"ay":624},"126,0":{"ax":192,"ay":624},"126,1":{"ax":216,"ay":624},"126,2":{"ax":240,"ay":624},"126,3":{"ax":264,"ay":624},"126,4":{"ax":288,"ay":624},"126,5":{"ax":312,"ay":624},"126,6":{"ax":336,"ay":624},"126,7":{"ax":360,"ay":624},"126,8":{"ax":384,"ay":624},"127,0":{"ax":408,"ay":624},"127,1":{"ax":432,"ay":624},"127,2":{"ax":456,"ay":624},"127,3":{"ax":480,"ay":624},"127,4":{"ax":504,"ay":624},"127,5":{"ax":528,"ay":624},"128,0":{"ax":552,"ay":624},"128,1":{"ax":576,"ay":624},"128,2":{"ax":600,"ay":624},"128,3":{"ax":624,"ay":624},"128,4":{"ax":648,"ay":624},"128,5":{"ax":672,"ay":624},"129,0":{"ax":696,"ay":624},"129,1":{"ax":720,"ay":624},"129,2":{"ax":744,"ay":624},"129,3":{"ax":0,"ay":648},"129,4":{"ax":24,"ay":648},"129,5":{"ax":48,"ay":648},"129,6":{"ax":72,"ay":648},"129,7":{"ax":96,"ay":648},"129,8":{"ax":120,"ay":648},"130,0":{"ax":144,"ay":648},"130,1":{"ax":168,"ay":648},"130,2":{"ax":192,"ay":648},"130,3":{"ax":216,"ay":648},"130,4":{"ax":240,"ay":648},"130,5":{"ax":264,"ay":648},"130,6":{"ax":288,"ay":648},"130,7":{"ax":312,"ay":648},"130,8":{"ax":336,"ay":648},"131,0":{"ax":360,"ay":648},"131,1":{"ax":384,"ay":648},"131,2":{"ax":408,"ay":648},"131,3":{"ax":432,"ay":648},"131,4":{"ax":456,"ay":648},"131,5":{"ax":480,"ay":648},"131,6":{"ax":504,"ay":648},"131,7":{"ax":528,"ay":648},"131,8":{"ax":552,"ay":648},"131,9":{"ax":576,"ay":648},"132,0":{"ax":600,"ay":648},"132,1":{"ax":624,"ay":648},"132,2":{"ax":648,"ay":648},"132,3":{"ax":672,"ay":648},"132,4":{"ax":696,"ay":648},"132,5":{"ax":720,"ay":648},"132,6":{"ax":744,"ay":648},"132,7":{"ax":0,"ay":672},"132,8":{"ax":24,"ay":672},"132,9":{"ax":48,"ay":672},"133,0":{"ax":72,"ay":672},"133,1":{"ax":96,"ay":672},"133,2":{"ax":120,"ay":672},"133,3":{"ax":144,"ay":672},"133,4":{"ax":168,"ay":672},"133,5":{"ax":192,"ay":672},"133,6":{"ax":216,"ay":672},"133,7":{"ax":240,"ay":672},"133,8":{"ax":264,"ay":672},"134,0":{"ax":288,"ay":672},"134,1":{"ax":312,"ay":672},"134,2":{"ax":336,"ay":672},"134,3":{"ax":360,"ay":672},"134,4":{"ax":384,"ay":672},"134,5":{"ax":408,"ay":672},"134,6":{"ax":432,"ay":672},"134,7":{"ax":456,"ay":672},"134,8":{"ax":480,"ay":672},"135,0":{"ax":504,"ay":672},"135,1":{"ax":528,"ay":672},"135,2":{"ax":552,"ay":672},"135,3":{"ax":576,"ay":672},"136,0":{"ax":600,"ay":672},"136,1":{"ax":624,"ay":672},"136,2":{"ax":648,"ay":672},"136,3":{"ax":672,"ay":672},"136,4":{"ax":696,"ay":672},"136,5":{"ax":720,"ay":672},"137,0":{"ax":744,"ay":672},"137,1":{"ax":0,"ay":696},"137,2":{"ax":24,"ay":696},"137,3":{"ax":48,"ay":696},"138,0":{"ax":72,"ay":696},"138,1":{"ax":96,"ay":696},"138,2":{"ax":120,"ay":696},"138,3":{"ax":144,"ay":696},"139,0":{"ax":168,"ay":696},"139,1":{"ax":192,"ay":696},"139,2":{"ax":216,"ay":696},"139,3":{"ax":240,"ay":696},"140,0":{"ax":264,"ay":696},"140,1":{"ax":288,"ay":696},"140,2":{"ax":312,"ay":696},"140,3":{"ax":336,"ay":696},"140,4":{"ax":360,"ay":696},"141,0":{"ax":384,"ay":696},"141,1":{"ax":408,"ay":696},"141,2":{"ax":432,"ay":696},"141,3":{"ax":456,"ay":696},"142,0":{"ax":480,"ay":696},"142,1":{"ax":504,"ay":696},"142,2":{"ax":528,"ay":696},"142,3":{"ax":552,"ay":696},"143,0":{"ax":576,"ay":696},"143,1":{"ax":600,"ay":696},"143,2":{"ax":624,"ay":696},"143,3":{"ax":648,"ay":696},"143,4":{"ax":672,"ay":696},"143,5":{"ax":696,"ay":696},"144,0":{"ax":720,"ay":696},"144,1":{"ax":744,"ay":696},"144,2":{"ax":0,"ay":720},"144,3":{"ax":24,"ay":720},"145,0":{"ax":48,"ay":720},"145,1":{"ax":72,"ay":720},"145,2":{"ax":96,"ay":720},"145,3":{"ax":120,"ay":720},"146,0":{"ax":144,"ay":720},"146,1":{"ax":168,"ay":720},"146,2":{"ax":192,"ay":720},"146,3":{"ax":216,"ay":720},"147,0":{"ax":240,"ay":720},"147,1":{"ax":264,"ay":720},"147,2":{"ax":288,"ay":720},"147,3":{"ax":312,"ay":720},"147,4":{"ax":336,"ay":720},"147,5":{"ax":360,"ay":720},"148,0":{"ax":384,"ay":720},"148,1":{"ax":408,"ay":720},"148,2":{"ax":432,"ay":720},"149,0":{"ax":456,"ay":720},"149,1":{"ax":480,"ay":720},"149,2":{"ax":504,"ay":720},"149,3":{"ax":528,"ay":720},"150,0":{"ax":552,"ay":720},"150,1":{"ax":576,"ay":720},"150,2":{"ax":600,"ay":720},"150,3":{"ax":624,"ay":720},"151,0":{"ax":648,"ay":720},"151,1":{"ax":672,"ay":720},"151,2":{"ax":696,"ay":720},"151,3":{"ax":720,"ay":720},"152,0":{"ax":744,"ay":720},"152,1":{"ax":0,"ay":744},"152,2":{"ax":24,"ay":744},"152,3":{"ax":48,"ay":744},"153,0":{"ax":72,"ay":744},"153,1":{"ax":96,"ay":744},"153,2":{"ax":120,"ay":744},"153,3":{"ax":144,"ay":744},"154,0":{"ax":168,"ay":744},"154,1":{"ax":192,"ay":744},"154,2":{"ax":216,"ay":744},"154,3":{"ax":240,"ay":744},"154,4":{"ax":264,"ay":744},"155,0":{"ax":288,"ay":744},"155,1":{"ax":312,"ay":744},"156,0":{"ax":336,"ay":744},"156,1":{"ax":360,"ay":744},"157,0":{"ax":384,"ay":744},"157,1":{"ax":408,"ay":744},"157,2":{"ax":432,"ay":744},"157,3":{"ax":456,"ay":744},"157,4":{"ax":480,"ay":744},"157,5":{"ax":504,"ay":744},"158,0":{"ax":528,"ay":744},"158,1":{"ax":552,"ay":744},"158,2":{"ax":576,"ay":744},"158,3":{"ax":600,"ay":744},"159,0":{"ax":624,"ay":744},"159,1":{"ax":648,"ay":744},"159,2":{"ax":672,"ay":744},"159,3":{"ax":696,"ay":744},"160,0":{"ax":720,"ay":744},"160,1":{"ax":744,"ay":744},"160,2":{"ax":0,"ay":768},"160,3":{"ax":24,"ay":768},"161,0":{"ax":48,"ay":768},"161,1":{"ax":72,"ay":768},"161,2":{"ax":96,"ay":768},"161,3":{"ax":120,"ay":768},"161,4":{"ax":144,"ay":768},"161,5":{"ax":168,"ay":768},"162,0":{"ax":192,"ay":768},"162,1":{"ax":216,"ay":768},"162,2":{"ax":240,"ay":768},"163,0":{"ax":264,"ay":768},"163,1":{"ax":288,"ay":768},"163,2":{"ax":312,"ay":768},"163,3":{"ax":336,"ay":768},"164,0":{"ax":360,"ay":768},"164,1":{"ax":384,"ay":768},"164,2":{"ax":408,"ay":768},"164,3":{"ax":432,"ay":768},"165,0":{"ax":456,"ay":768},"165,1":{"ax":480,"ay":768},"165,2":{"ax":504,"ay":768},"165,3":{"ax":528,"ay":768},"166,0":{"ax":552,"ay":768},"166,1":{"ax":576,"ay":768},"166,2":{"ax":600,"ay":768},"167,0":{"ax":624,"ay":768},"167,1":{"ax":648,"ay":768},"167,2":{"ax":672,"ay":768},"167,3":{"ax":696,"ay":768},"168,0":{"ax":720,"ay":768},"168,1":{"ax":744,"ay":768},"168,2":{"ax":0,"ay":792},"168,3":{"ax":24,"ay":792},"169,0":{"ax":48,"ay":792},"169,1":{"ax":72,"ay":792},"169,2":{"ax":96,"ay":792},"169,3":{"ax":120,"ay":792},"170,0":{"ax":144,"ay":792},"170,1":{"ax":168,"ay":792},"170,2":{"ax":192,"ay":792},"170,3":{"ax":216,"ay":792},"171,0":{"ax":240,"ay":792},"171,1":{"ax":264,"ay":792},"171,2":{"ax":288,"ay":792},"171,3":{"ax":312,"ay":792},"172,0":{"ax":336,"ay":792},"172,1":{"ax":360,"ay":792},"172,2":{"ax":384,"ay":792},"172,3":{"ax":408,"ay":792},"173,0":{"ax":432,"ay":792},"173,1":{"ax":456,"ay":792},"173,2":{"ax":480,"ay":792},"174,0":{"ax":504,"ay":792},"174,1":{"ax":528,"ay":792},"174,2":{"ax":552,"ay":792},"174,3":{"ax":576,"ay":792},"175,0":{"ax":600,"ay":792},"175,1":{"ax":624,"ay":792},"176,0":{"ax":648,"ay":792},"176,1":{"ax":672,"ay":792},"176,2":{"ax":696,"ay":792},"177,0":{"ax":720,"ay":792},"177,1":{"ax":744,"ay":792},"177,2":{"ax":0,"ay":816},"177,3":{"ax":24,"ay":816},"177,4":{"ax":48,"ay":816},"177,5":{"ax":72,"ay":816},"177,6":{"ax":96,"ay":816},"177,7":{"ax":120,"ay":816},"178,0":{"ax":144,"ay":816},"178,1":{"ax":168,"ay":816},"178,2":{"ax":192,"ay":816},"178,3":{"ax":216,"ay":816},"178,4":{"ax":240,"ay":816},"179,0":{"ax":264,"ay":816},"179,1":{"ax":288,"ay":816},"179,2":{"ax":312,"ay":816},"179,3":{"ax":336,"ay":816},"179,4":{"ax":360,"ay":816},"180,0":{"ax":384,"ay":816},"180,1":{"ax":408,"ay":816},"180,2":{"ax":432,"ay":816},"180,3":{"ax":456,"ay":816},"181,0":{"ax":480,"ay":816},"181,1":{"ax":504,"ay":816},"181,2":{"ax":528,"ay":816},"181,3":{"ax":552,"ay":816},"181,4":{"ax":576,"ay":816},"181,5":{"ax":600,"ay":816},"181,6":{"ax":624,"ay":816},"181,7":{"ax":648,"ay":816},"181,8":{"ax":672,"ay":816},"181,9":{"ax":696,"ay":816},"182,0":{"ax":720,"ay":816},"182,1":{"ax":744,"ay":816},"182,2":{"ax":0,"ay":840},"182,3":{"ax":24,"ay":840},"182,4":{"ax":48,"ay":840},"182,5":{"ax":72,"ay":840},"183,0":{"ax":96,"ay":840},"183,1":{"ax":120,"ay":840},"183,2":{"ax":144,"ay":840},"183,3":{"ax":168,"ay":840},"184,0":{"ax":192,"ay":840},"184,1":{"ax":216,"ay":840},"184,2":{"ax":240,"ay":840},"185,0":{"ax":264,"ay":840},"185,1":{"ax":288,"ay":840},"185,2":{"ax":312,"ay":840},"185,3":{"ax":336,"ay":840},"185,4":{"ax":360,"ay":840},"185,5":{"ax":384,"ay":840},"185,6":{"ax":408,"ay":840},"185,7":{"ax":432,"ay":840},"185,8":{"ax":456,"ay":840},"186,0":{"ax":480,"ay":840},"186,1":{"ax":504,"ay":840},"186,2":{"ax":528,"ay":840},"186,3":{"ax":552,"ay":840},"186,4":{"ax":576,"ay":840},"186,5":{"ax":600,"ay":840},"186,6":{"ax":624,"ay":840},"186,7":{"ax":648,"ay":840},"187,0":{"ax":672,"ay":840},"187,1":{"ax":696,"ay":840},"187,2":{"ax":720,"ay":840},"187,3":{"ax":744,"ay":840},"187,4":{"ax":0,"ay":864},"187,5":{"ax":24,"ay":864},"187,6":{"ax":48,"ay":864},"187,7":{"ax":72,"ay":864},"188,0":{"ax":96,"ay":864},"188,1":{"ax":120,"ay":864},"188,2":{"ax":144,"ay":864},"188,3":{"ax":168,"ay":864},"188,4":{"ax":192,"ay":864},"188,5":{"ax":216,"ay":864},"188,6":{"ax":240,"ay":864},"188,7":{"ax":264,"ay":864},"188,8":{"ax":288,"ay":864},"189,0":{"ax":312,"ay":864},"189,1":{"ax":336,"ay":864},"189,2":{"ax":360,"ay":864},"189,3":{"ax":384,"ay":864},"189,4":{"ax":408,"ay":864},"189,5":{"ax":432,"ay":864},"190,0":{"ax":456,"ay":864},"190,1":{"ax":480,"ay":864},"190,2":{"ax":504,"ay":864},"190,3":{"ax":528,"ay":864},"190,4":{"ax":552,"ay":864},"190,5":{"ax":576,"ay":864},"190,6":{"ax":600,"ay":864},"190,7":{"ax":624,"ay":864},"190,8":{"ax":648,"ay":864},"191,0":{"ax":672,"ay":864},"191,1":{"ax":696,"ay":864},"191,2":{"ax":720,"ay":864},"191,3":{"ax":744,"ay":864},"191,4":{"ax":0,"ay":888},"191,5":{"ax":24,"ay":888},"191,6":{"ax":48,"ay":888},"191,7":{"ax":72,"ay":888},"191,8":{"ax":96,"ay":888},"192,0":{"ax":120,"ay":888},"192,1":{"ax":144,"ay":888},"192,2":{"ax":168,"ay":888},"192,3":{"ax":192,"ay":888},"192,4":{"ax":216,"ay":888},"192,5":{"ax":240,"ay":888},"192,6":{"ax":264,"ay":888},"192,7":{"ax":288,"ay":888},"193,0":{"ax":312,"ay":888},"193,1":{"ax":336,"ay":888},"193,2":{"ax":360,"ay":888},"193,3":{"ax":384,"ay":888},"193,4":{"ax":408,"ay":888},"193,5":{"ax":432,"ay":888},"194,0":{"ax":456,"ay":888},"194,1":{"ax":480,"ay":888},"194,2":{"ax":504,"ay":888},"194,3":{"ax":528,"ay":888},"194,4":{"ax":552,"ay":888},"194,5":{"ax":576,"ay":888},"194,6":{"ax":600,"ay":888},"195,0":{"ax":624,"ay":888},"195,1":{"ax":648,"ay":888},"195,2":{"ax":672,"ay":888},"195,3":{"ax":696,"ay":888},"195,4":{"ax":720,"ay":888},"195,5":{"ax":744,"ay":888},"195,6":{"ax":0,"ay":912},"196,0":{"ax":24,"ay":912},"196,1":{"ax":48,"ay":912},"196,2":{"ax":72,"ay":912},"196,3":{"ax":96,"ay":912},"196,4":{"ax":120,"ay":912},"196,5":{"ax":144,"ay":912},"196,6":{"ax":168,"ay":912},"197,0":{"ax":192,"ay":912},"197,1":{"ax":216,"ay":912},"197,2":{"ax":240,"ay":912},"197,3":{"ax":264,"ay":912},"197,4":{"ax":288,"ay":912},"197,5":{"ax":312,"ay":912},"197,6":{"ax":336,"ay":912},"198,0":{"ax":360,"ay":912},"198,1":{"ax":384,"ay":912},"199,0":{"ax":408,"ay":912},"199,1":{"ax":432,"ay":912},"200,0":{"ax":456,"ay":912},"200,1":{"ax":480,"ay":912},"200,2":{"ax":504,"ay":912},"201,0":{"ax":528,"ay":912},"201,1":{"ax":552,"ay":912},"201,2":{"ax":576,"ay":912},"202,0":{"ax":600,"ay":912},"202,1":{"ax":624,"ay":912},"202,2":{"ax":648,"ay":912},"203,0":{"ax":672,"ay":912},"203,1":{"ax":696,"ay":912},"203,2":{"ax":720,"ay":912},"204,0":{"ax":744,"ay":912},"204,1":{"ax":0,"ay":936},"204,2":{"ax":24,"ay":936},"205,0":{"ax":48,"ay":936},"205,1":{"ax":72,"ay":936},"205,2":{"ax":96,"ay":936},"206,0":{"ax":120,"ay":936},"206,1":{"ax":144,"ay":936},"206,2":{"ax":168,"ay":936},"206,3":{"ax":192,"ay":936},"206,4":{"ax":216,"ay":936},"206,5":{"ax":240,"ay":936},"206,6":{"ax":264,"ay":936},"207,0":{"ax":288,"ay":936},"207,1":{"ax":312,"ay":936},"207,2":{"ax":336,"ay":936},"207,3":{"ax":360,"ay":936},"207,4":{"ax":384,"ay":936},"207,5":{"ax":408,"ay":936},"207,6":{"ax":432,"ay":936},"208,0":{"ax":456,"ay":936},"208,1":{"ax":480,"ay":936},"209,0":{"ax":504,"ay":936},"209,1":{"ax":528,"ay":936},"210,0":{"ax":552,"ay":936},"210,1":{"ax":576,"ay":936},"210,2":{"ax":600,"ay":936},"211,0":{"ax":624,"ay":936},"211,1":{"ax":648,"ay":936},"211,2":{"ax":672,"ay":936},"212,0":{"ax":696,"ay":936},"212,1":{"ax":720,"ay":936},"212,2":{"ax":744,"ay":936},"213,0":{"ax":0,"ay":960},"213,1":{"ax":24,"ay":960},"213,2":{"ax":48,"ay":960},"214,0":{"ax":72,"ay":960},"214,1":{"ax":96,"ay":960},"214,2":{"ax":120,"ay":960},"215,0":{"ax":144,"ay":960},"215,1":{"ax":168,"ay":960},"215,2":{"ax":192,"ay":960},"216,0":{"ax":216,"ay":960},"217,0":{"ax":240,"ay":960},"218,0":{"ax":264,"ay":960},"219,0":{"ax":288,"ay":960},"220,0":{"ax":312,"ay":960},"221,0":{"ax":336,"ay":960},"222,0":{"ax":360,"ay":960},"223,0":{"ax":384,"ay":960},"223,1":{"ax":408,"ay":960},"224,0":{"ax":432,"ay":960},"224,1":{"ax":456,"ay":960},"225,0":{"ax":480,"ay":960},"225,1":{"ax":504,"ay":960},"226,0":{"ax":528,"ay":960},"226,1":{"ax":552,"ay":960},"227,0":{"ax":576,"ay":960},"228,0":{"ax":600,"ay":960},"229,0":{"ax":624,"ay":960},"229,1":{"ax":648,"ay":960},"230,0":{"ax":672,"ay":960},"230,1":{"ax":696,"ay":960},"231,0":{"ax":720,"ay":960},"231,1":{"ax":744,"ay":960},"231,2":{"ax":0,"ay":984},"231,3":{"ax":24,"ay":984},"232,0":{"ax":48,"ay":984},"232,1":{"ax":72,"ay":984},"232,2":{"ax":96,"ay":984},"232,3":{"ax":120,"ay":984},"233,0":{"ax":144,"ay":984},"233,1":{"ax":168,"ay":984},"233,2":{"ax":192,"ay":984},"233,3":{"ax":216,"ay":984},"234,0":{"ax":240,"ay":984},"234,1":{"ax":264,"ay":984},"234,2":{"ax":288,"ay":984},"234,3":{"ax":312,"ay":984},"235,0":{"ax":336,"ay":984},"235,1":{"ax":360,"ay":984},"235,2":{"ax":384,"ay":984},"235,3":{"ax":408,"ay":984},"235,4":{"ax":432,"ay":984},"235,5":{"ax":456,"ay":984},"235,6":{"ax":480,"ay":984},"235,7":{"ax":504,"ay":984},"236,0":{"ax":528,"ay":984},"236,1":{"ax":552,"ay":984},"236,2":{"ax":576,"ay":984},"236,3":{"ax":600,"ay":984},"236,4":{"ax":624,"ay":984},"236,5":{"ax":648,"ay":984},"236,6":{"ax":672,"ay":984},"236,7":{"ax":696,"ay":984},"236,8":{"ax":720,"ay":984},"237,0":{"ax":744,"ay":984},"237,1":{"ax":0,"ay":1008},"237,2":{"ax":24,"ay":1008},"237,3":{"ax":48,"ay":1008},"237,4":{"ax":72,"ay":1008},"237,5":{"ax":96,"ay":1008},"237,6":{"ax":120,"ay":1008},"237,7":{"ax":144,"ay":1008},"237,8":{"ax":168,"ay":1008},"238,0":{"ax":192,"ay":1008},"238,1":{"ax":216,"ay":1008},"238,2":{"ax":240,"ay":1008},"238,3":{"ax":264,"ay":1008},"238,4":{"ax":288,"ay":1008},"238,5":{"ax":312,"ay":1008},"238,6":{"ax":336,"ay":1008},"238,7":{"ax":360,"ay":1008},"238,8":{"ax":384,"ay":1008},"238,9":{"ax":408,"ay":1008},"239,0":{"ax":432,"ay":1008},"239,1":{"ax":456,"ay":1008},"239,2":{"ax":480,"ay":1008},"239,3":{"ax":504,"ay":1008},"239,4":{"ax":528,"ay":1008},"239,5":{"ax":552,"ay":1008},"239,6":{"ax":576,"ay":1008},"239,7":{"ax":600,"ay":1008},"239,8":{"ax":624,"ay":1008},"239,9":{"ax":648,"ay":1008},"240,0":{"ax":672,"ay":1008},"240,1":{"ax":696,"ay":1008},"240,2":{"ax":720,"ay":1008},"240,3":{"ax":744,"ay":1008},"240,4":{"ax":0,"ay":1032},"240,5":{"ax":24,"ay":1032},"240,6":{"ax":48,"ay":1032},"240,7":{"ax":72,"ay":1032},"240,8":{"ax":96,"ay":1032},"240,9":{"ax":120,"ay":1032},"241,0":{"ax":144,"ay":1032},"241,1":{"ax":168,"ay":1032},"241,2":{"ax":192,"ay":1032},"241,3":{"ax":216,"ay":1032},"241,4":{"ax":240,"ay":1032},"242,0":{"ax":264,"ay":1032},"242,1":{"ax":288,"ay":1032},"242,2":{"ax":312,"ay":1032},"242,3":{"ax":336,"ay":1032},"242,4":{"ax":360,"ay":1032},"243,0":{"ax":384,"ay":1032},"243,1":{"ax":408,"ay":1032},"243,2":{"ax":432,"ay":1032},"243,3":{"ax":456,"ay":1032},"243,4":{"ax":480,"ay":1032},"244,0":{"ax":504,"ay":1032},"244,1":{"ax":528,"ay":1032},"244,2":{"ax":552,"ay":1032},"244,3":{"ax":576,"ay":1032},"244,4":{"ax":600,"ay":1032},"245,0":{"ax":624,"ay":1032},"245,1":{"ax":648,"ay":1032},"245,2":{"ax":672,"ay":1032},"245,3":{"ax":696,"ay":1032},"245,4":{"ax":720,"ay":1032},"246,0":{"ax":744,"ay":1032},"246,1":{"ax":0,"ay":1056},"246,2":{"ax":24,"ay":1056},"246,3":{"ax":48,"ay":1056},"246,4":{"ax":72,"ay":1056},"247,0":{"ax":96,"ay":1056},"247,1":{"ax":120,"ay":1056},"247,2":{"ax":144,"ay":1056},"247,3":{"ax":168,"ay":1056},"247,4":{"ax":192,"ay":1056},"247,5":{"ax":216,"ay":1056},"247,6":{"ax":240,"ay":1056},"247,7":{"ax":264,"ay":1056},"247,8":{"ax":288,"ay":1056},"248,0":{"ax":312,"ay":1056},"248,1":{"ax":336,"ay":1056},"248,2":{"ax":360,"ay":1056},"248,3":{"ax":384,"ay":1056},"248,4":{"ax":408,"ay":1056},"248,5":{"ax":432,"ay":1056},"248,6":{"ax":456,"ay":1056},"248,7":{"ax":480,"ay":1056},"248,8":{"ax":504,"ay":1056},"249,0":{"ax":528,"ay":1056},"249,1":{"ax":552,"ay":1056},"249,2":{"ax":576,"ay":1056},"249,3":{"ax":600,"ay":1056},"249,4":{"ax":624,"ay":1056},"249,5":{"ax":648,"ay":1056},"249,6":{"ax":672,"ay":1056},"249,7":{"ax":696,"ay":1056},"249,8":{"ax":720,"ay":1056},"250,0":{"ax":744,"ay":1056},"250,1":{"ax":0,"ay":1080},"250,2":{"ax":24,"ay":1080},"250,3":{"ax":48,"ay":1080},"250,4":{"ax":72,"ay":1080},"250,5":{"ax":96,"ay":1080},"250,6":{"ax":120,"ay":1080},"250,7":{"ax":144,"ay":1080},"250,8":{"ax":168,"ay":1080},"251,0":{"ax":192,"ay":1080},"251,1":{"ax":216,"ay":1080},"251,2":{"ax":240,"ay":1080},"251,3":{"ax":264,"ay":1080},"251,4":{"ax":288,"ay":1080},"251,5":{"ax":312,"ay":1080},"251,6":{"ax":336,"ay":1080},"251,7":{"ax":360,"ay":1080},"251,8":{"ax":384,"ay":1080},"252,0":{"ax":408,"ay":1080},"252,1":{"ax":432,"ay":1080},"252,2":{"ax":456,"ay":1080},"252,3":{"ax":480,"ay":1080},"252,4":{"ax":504,"ay":1080},"252,5":{"ax":528,"ay":1080},"252,6":{"ax":552,"ay":1080},"252,7":{"ax":576,"ay":1080},"252,8":{"ax":600,"ay":1080},"255,0":{"ax":624,"ay":1080}}}